defaultcontext/__init__.py
defaultcontext/stack.py
defaultcontext/wrappers.py
defaultcontext-1.1.1.dist-info/DESCRIPTION.rst
defaultcontext-1.1.1.dist-info/METADATA
defaultcontext-1.1.1.dist-info/RECORD
defaultcontext-1.1.1.dist-info/WHEEL
defaultcontext-1.1.1.dist-info/metadata.json
defaultcontext-1.1.1.dist-info/top_level.txt
